{
	"apps": {
		"AD EBiS": {
			"cats": [
				10
			],
			"html": [
				"<!-- EBiS contents tag",
				"<!--EBiS tag",
				"<!-- Tag EBiS",
				"<!-- EBiS common tag"
			],
			"icon": "ebis.png",
			"website": "http://www.ebis.ne.jp"
		},
		"AT Internet Analyzer": {
			"cats": [
				10
			],
			"js": {
				"xtsite": "",
				"ATInternet": ""
			},
			"icon": "AT Internet.png",
			"website": "http://atinternet.com/en"
		},
		"AT Internet XiTi": {
			"cats": [
				10
			],
			"js": {
				"xt_click": ""
			},
			"icon": "AT Internet.png",
			"script": "xiti\\.com/hit\\.xiti",
			"website": "http://atinternet.com/en"
		},
		"AWStats": {
			"cats": [
				10
			],
			"icon": "AWStats.png",
			"implies": "Perl",
			"meta": {
				"generator": "AWStats ([\\d.]+(?: \\(build [\\d.]+\\))?)\\;version:\\1"
			},
			"website": "http://awstats.sourceforge.net"
		},
		"Act-On": {
			"cats": [
				32
			],
			"js": {
				"ActOn": ""
			},
			"icon": "ActOn.png",
			"website": "http://act-on.com"
		},
		"AdInfinity": {
			"cats": [
				36
			],
			"icon": "AdInfinity.png",
			"script": "adinfinity\\.com\\.au",
			"website": "http://adinfinity.com.au"
		},
		"AdRiver": {
			"cats": [
				36
			],
			"js": {
				"adriver": ""
			},
			"html": "(?:<embed[^>]+(?:src=\"https?://mh\\d?\\.adriver\\.ru/|flashvars=\"[^\"]*(?:http:%3A//(?:ad|mh\\d?)\\.adriver\\.ru/|adriver_banner))|<(?:(?:iframe|img)[^>]+src|a[^>]+href)=\"https?://ad\\.adriver\\.ru/)",
			"icon": "AdRiver.png",
			"script": "(?:adriver\\.core\\.\\d\\.js|https?://(?:content|ad|masterh\\d)\\.adriver\\.ru/)",
			"website": "http://adriver.ru"
		},
		"AdRoll": {
			"cats": [
				36
			],
			"js": {
				"adroll_adv_id": "",
				"adroll_pix_id": ""
			},
			"icon": "AdRoll.svg",
			"script": "(?:a|s)\\.adroll\\.com",
			"website": "http://adroll.com"
		},
		"Adcash": {
			"cats": [
				36
			],
			"js": {
				"ac_bgclick_URL": "",
				"ct_siteunder": "",
				"ct_tag": "",
				"ct_nSuUrl": "",
				"ct_nOpp": "",
				"SuLoaded": "",
				"SuUrl": ""
			},
			"icon": "Adcash.svg",
			"script": "^[^\\/]*//(?:[^\\/]+\\.)?adcash\\.com/(?:script|ad)/",
			"url": "^https?://(?:[^\\/]+\\.)?adcash\\.com/script/pop_",
			"website": "http://adcash.com"
		},
		"AddShoppers": {
			"cats": [
				5
			],
			"icon": "AddShoppers.png",
			"script": "cdn\\.shop\\.pe/widget/",
			"website": "http://www.addshoppers.com"
		},
		"AddThis": {
			"cats": [
				5
			],
			"js": {
				"addthis": ""
			},
			"icon": "AddThis.svg",
			"script": "addthis\\.com/js/",
			"website": "http://www.addthis.com"
		},
		"AddToAny": {
			"cats": [
				5
			],
			"js": {
				"a2apage_init": ""
			},
			"icon": "AddToAny.png",
			"script": "addtoany\\.com/menu/page\\.js",
			"website": "http://www.addtoany.com"
		},
		"Adnegah": {
			"cats": [
				36
			],
			"headers": {
				"X-Advertising-By": "adnegah\\.net"
			},
			"html": "<iframe [^>]*src=\"[^\"]+adnegah\\.net",
			"icon": "adnegah.png",
			"script": "[^a-z]adnegah.*\\.js$",
			"website": "https://Adnegah.net"
		},
		"Advanced Web Stats": {
			"cats": [
				10
			],
			"html": "aws\\.src = [^<]+caphyon-analytics",
			"icon": "Advanced Web Stats.png",
			"implies": "Java",
			"website": "http://www.advancedwebstats.com"
		},
		"Advert Stream": {
			"cats": [
				36
			],
			"js": {
				"advst_is_above_the_fold": ""
			},
			"icon": "Advert Stream.png",
			"script": "(?:ad\\.advertstream\\.com|adxcore\\.com)",
			"website": "http://www.advertstream.com"
		},
		"Adzerk": {
			"cats": [
				36
			],
			"js": {
				"ados": "",
				"adosResults": ""
			},
			"html": "<iframe [^>]*src=\"[^\"]+adzerk\\.net",
			"icon": "Adzerk.png",
			"script": "adzerk\\.net/ados\\.js",
			"website": "http://adzerk.com"
		},
		"Aircall": {
			"cats": [
				52
			],
			"icon": "aircall.png",
			"script": "^https?://cdn\\.aircall\\.io/",
			"website": "http://aircall.io"
		},
		"Airee": {
			"cats": [
				31
			],
			"headers": {
				"Server": "^Airee"
			},
			"icon": "Airee.png",
			"website": "http://xn--80aqc2a.xn--p1ai"
		},
		"Akamai": {
			"cats": [
				31
			],
			"headers": {
				"X-Akamai-Transformed": ""
			},
			"icon": "akamai.svg",
			"website": "http://akamai.com"
		},
		"Amazon Cloudfront": {
			"cats": [
				31
			],
			"headers": {
				"X-Amz-Cf-Id": "",
				"Via": "\\(CloudFront\\)$"
			},
			"icon": "Amazon-Cloudfront.svg",
			"website": "http://aws.amazon.com/cloudfront/"
		},
		"AppNexus": {
			"cats": [
				36
			],
			"html": "<(?:iframe|img)[^>]+adnxs\\.(?:net|com)",
			"icon": "AppNexus.svg",
			"script": "adnxs\\.(?:net|com)",
			"website": "http://appnexus.com"
		},
		"ArcGIS API for JavaScript": {
			"cats": [
				35
			],
			"script": [
				"js\\.arcgis\\.com",
				"basemaps\\.arcgis\\.com"
			],
			"icon": "arcgis_icon.png",
			"website": "https://developers.arcgis.com/javascript/"
		},
		"ArvanCloud": {
			"cats": [
				31
			],
			"js": {
				"ArvanCloud": ""
			},
			"headers": {
				"AR-PoweredBy": "Arvan Cloud \\(arvancloud\\.com\\)"
			},
			"icon": "ArvanCloud.png",
			"website": "http://www.ArvanCloud.com"
		},
		"Asciinema": {
			"cats": [
				14
			],
			"js": {
				"asciinema": ""
			},
			"script": "asciinema\\.org/",
			"icon": "asciinema.png",
			"html": "<asciinema-player",
			"website": "https://asciinema.org/"
		},
		"Backtory": {
			"cats": [
				31
			],
			"headers": {
				"X-Powered-By": "Backtory"
			},
			"icon": "Backtory.svg",
			"website": "https://backtory.com"
		},
		"BittAds": {
			"cats": [
				36
			],
			"js": {
				"bitt": ""
			},
			"icon": "BittAds.png",
			"script": "bittads\\.com/js/bitt\\.js$",
			"website": "http://bittads.com"
		},
		"Blip.tv": {
			"cats": [
				14
			],
			"html": "<(?:param|embed|iframe)[^>]+blip\\.tv/play",
			"icon": "Blip.tv.png",
			"website": "http://blip.tv"
		},
		"Bold Chat": {
			"cats": [
				52
			],
			"icon": "BoldChat.png",
			"script": "^https?://vmss\\.boldchat\\.com/aid/\\d{18}/bc\\.vms4/vms\\.js",
			"website": "https://www.boldchat.com/"
		},
		"Bounce Exchange": {
			"cats": [
				32
			],
			"js": {
				"bouncex": ""
			},
			"html": "<script[^>]*>[^>]+\\.src\\s*=\\s*['\"](?:https?:)?//tag\\.bounceexchange\\.com/",
			"icon": "Bounce Exchange.svg",
			"script": "^https?://tag\\.bounceexchange\\.com/",
			"website": "http://www.bounceexchange.com"
		},
		"BugSense": {
			"cats": [
				10
			],
			"js": {
				"Bugsense": ""
			},
			"icon": "BugSense.png",
			"script": "bugsense\\.js",
			"website": "http://bugsense.com"
		},
		"BugSnag": {
			"cats": [
				10
			],
			"js": {
				"Bugsnag": ""
			},
			"icon": "BugSnag.png",
			"script": "bugsnag.*\\.js",
			"website": "http://bugsnag.com"
		},
		"BuySellAds": {
			"cats": [
				36
			],
			"js": {
				"_bsa": "",
				"_bsap": "",
				"_bsaPRO": "",
				"_bsap_serving_callback": ""
			},
			"html": "<script[^>]*>[^<]+?bsa\\.src\\s*=\\s*['\"](?:https?:)?\\/{2}\\w\\d\\.buysellads\\.com\\/[\\w\\d\\/]+?bsa\\.js['\"]",
			"icon": "BuySellAds.png",
			"script": "^https?://s\\d\\.buysellads\\.com/",
			"website": "http://buysellads.com"
		},
		"CO2Stats": {
			"cats": [
				10
			],
			"html": "src=[^>]+co2stats\\.com/propres\\.php",
			"icon": "CO2Stats.png",
			"website": "http://co2stats.com"
		},
		"CacheFly": {
			"cats": [
				31
			],
			"headers": {
				"Server": "^CFS ",
				"X-CF1": "",
				"X-CF2": ""
			},
			"icon": "CacheFly.png",
			"website": "http://www.cachefly.com"
		},
		"Captch Me": {
			"cats": [
				16,
				36
			],
			"js": {
				"Captchme": ""
			},
			"icon": "Captch Me.svg",
			"script": "^https?://api\\.captchme\\.net/",
			"website": "http://captchme.com"
		},
		"Carbon Ads": {
			"cats": [
				36
			],
			"js": {
				"_carbonads": ""
			},
			"html": "<[a-z]+ [^>]*id=\"carbonads-container\"",
			"icon": "Carbon Ads.png",
			"script": "//(?:engine|srv)\\.carbonads\\.com\\/",
			"website": "http://carbonads.net"
		},
		"CDN77": {
			"cats": [
				31
			],
			"headers": {
				"Server": "^CDN77-Turbo$"
			},
			"icon": "CDN77.png",
			"website": "https://www.cdn77.com"
		},
		"Chartbeat": {
			"cats": [
				10
			],
			"js": {
				"_sf_endpt": "",
				"_sf_async_config": ""
			},
			"icon": "Chartbeat.png",
			"script": "chartbeat\\.js",
			"website": "http://chartbeat.com"
		},
		"Chitika": {
			"cats": [
				36
			],
			"js": {
				"ch_client": "",
				"ch_color_site_link": ""
			},
			"icon": "Chitika.png",
			"script": "scripts\\.chitika\\.net/",
			"website": "http://chitika.com"
		},
		"ClickHeat": {
			"cats": [
				10
			],
			"js": {
				"clickHeatServer": ""
			},
			"icon": "ClickHeat.png",
			"implies": "PHP",
			"script": "clickheat.*\\.js",
			"website": "http://www.labsmedia.com/clickheat/index.html"
		},
		"ClickTale": {
			"cats": [
				10
			],
			"js": {
				"clickTaleStartEventSignal": ""
			},
			"icon": "ClickTale.png",
			"website": "http://www.clicktale.com"
		},
		"Clicky": {
			"cats": [
				10
			],
			"js": {
				"clicky": ""
			},
			"icon": "Clicky.png",
			"script": "static\\.getclicky\\.com",
			"website": "http://getclicky.com"
		},
		"CloudFlare": {
			"cats": [
				31
			],
			"js": {
				"CloudFlare": ""
			},
			"headers": {
				"Server": "^cloudflare$"
			},
			"icon": "CloudFlare.svg",
			"website": "http://www.cloudflare.com"
		},
		"CoinHive Captcha": {
			"cats": [
				16,
				56
			],
			"html": "(?:<div[^>]+class=\"coinhive-captcha[^>]+data-key|<div[^>]+data-key[^>]+class=\"coinhive-captcha)",
			"script": "https?://authedmine\\.com/(?:lib/captcha|captcha)",
			"icon": "CoinHive.svg",
			"website": "https://coinhive.com"
		},
		"ConversionLab": {
			"cats": [
				10
			],
			"icon": "ConversionLab.png",
			"script": "conversionlab\\.trackset\\.com/track/tsend\\.js",
			"website": "http://www.trackset.it/conversionlab"
		},
		"Crazy Egg": {
			"cats": [
				10
			],
			"js": {
				"CE2": ""
			},
			"icon": "Crazy Egg.png",
			"script": "script\\.crazyegg\\.com/pages/scripts/\\d+/\\d+\\.js",
			"website": "http://crazyegg.com"
		},
		"Criteo": {
			"cats": [
				36
			],
			"js": {
				"Criteo": "",
				"criteo_pubtag": "",
				"criteo_q": ""
			},
			"icon": "Criteo.svg",
			"script": "//(?:cas\\.criteo\\.com|(?:[^/]\\.)?criteo\\.net)/",
			"website": "http://criteo.com"
		},
		"Cross Pixel": {
			"cats": [
				10
			],
			"js": {
				"cp_C4w1ldN2d9PmVrkN": ""
			},
			"icon": "Cross Pixel.png",
			"script": "tag\\.crsspxl\\.com/s1\\.js",
			"website": "http://datadesk.crsspxl.com"
		},
		"Disqus": {
			"cats": [
				15
			],
			"js": {
				"DISQUS": "",
				"disqus_shortname": "",
				"disqus_url": ""
			},
			"html": "<div[^>]+id=\"disqus_thread\"",
			"icon": "Disqus.svg",
			"script": "disqus_url",
			"website": "http://disqus.com"
		},
		"DoubleClick Ad Exchange (AdX)": {
			"cats": [
				36
			],
			"icon": "DoubleClick.svg",
			"script": [
				"googlesyndication\\.com/pagead/show_ads\\.js",
				"tpc\\.googlesyndication\\.com/safeframe",
				"googlesyndication\\.com.*abg\\.js"
			],
			"website": "http://www.doubleclickbygoogle.com/solutions/digital-marketing/ad-exchange/"
		},
		"DoubleClick Campaign Manager (DCM)": {
			"cats": [
				36
			],
			"icon": "DoubleClick.svg",
			"script": "2mdn\\.net",
			"website": "http://www.doubleclickbygoogle.com/solutions/digital-marketing/campaign-manager/"
		},
		"DoubleClick Floodlight": {
			"cats": [
				36
			],
			"icon": "DoubleClick.svg",
			"script": "https?://fls\\.doubleclick\\.net",
			"website": "http://support.google.com/ds/answer/6029713?hl=en"
		},
		"DoubleClick for Publishers (DFP)": {
			"cats": [
				36
			],
			"icon": "DoubleClick.svg",
			"script": "googletagservices\\.com/tag/js/gpt(?:_mobile)?\\.js",
			"website": "http://www.google.com/dfp"
		},
		"Dynamicweb": {
			"cats": [
				1,
				6,
				10
			],
			"cookies": {
				"Dynamicweb": ""
			},
			"icon": "Dynamicweb.png",
			"implies": "Microsoft ASP.NET",
			"meta": {
				"generator": "Dynamicweb ([\\d.]+)\\;version:\\1"
			},
			"website": "http://www.dynamicweb.dk"
		},
		"Dynatrace": {
			"cats": [
				10
			],
			"icon": "Dynatrace.png",
			"script": "dtagent.*\\.js",
			"website": "http://dynatrace.com"
		},
		"EdgeCast": {
			"cats": [
				31
			],
			"headers": {
				"Server": "^ECD\\s\\(\\S+\\)"
			},
			"icon": "EdgeCast.png",
			"url": "https?://(?:[^/]+\\.)?edgecastcdn\\.net/",
			"website": "http://www.edgecast.com"
		},
		"Eloqua": {
			"cats": [
				32
			],
			"js": {
				"elqSiteID": "",
				"elqLoad": "",
				"elqCurESite": "",
				"elq_global": ""
			},
			"icon": "Oracle.png",
			"script": "elqCfg\\.js",
			"website": "http://eloqua.com"
		},
		"Epom": {
			"cats": [
				36
			],
			"js": {
				"epomCustomParams": ""
			},
			"icon": "Epom.png",
			"url": "^https?://(?:[^/]+\\.)?ad(?:op)?shost1\\.com/",
			"website": "http://epom.com"
		},
		"Facebook": {
			"cats": [
				5
			],
			"icon": "Facebook.svg",
			"script": "//connect\\.facebook\\.net/[^/]*/[a-z]*\\.js",
			"website": "http://facebook.com"
		},
		"Fastly": {
			"cats": [
				31
			],
			"headers": {
				"Fastly-Debug-Digest": "",
				"Vary": "Fastly-SSL",
				"X-Fastly-Request-ID": ""
			},
			"icon": "Fastly.svg",
			"website": "https://www.fastly.com"
		},
		"Fireblade": {
			"cats": [
				31
			],
			"headers": {
				"Server": "fbs"
			},
			"icon": "Fireblade.png",
			"website": "http://fireblade.com"
		},
		"FlexSlider": {
			"cats": [
				5
			],
			"icon": "FlexSlider.png",
			"implies": "jQuery",
			"script": [
				"jquery\\.flexslider(?:\\.min)?\\.js$"
			],
			"website": "https://woocommerce.com/flexslider/"
		},
		"Freespee": {
			"cats": [
				10
			],
			"script": "analytics\\.freespee\\.com/js/external/fs\\.(?:min\\.)?js",
			"icon": "Freespee.svg",
			"website": "https://www.freespee.com"
		},
		"Fusion Ads": {
			"cats": [
				36
			],
			"js": {
				"_fusion": ""
			},
			"icon": "Fusion Ads.png",
			"script": "^[^\\/]*//[ac]dn\\.fusionads\\.net/(?:api/([\\d.]+)/)?\\;version:\\1",
			"website": "http://fusionads.net"
		},
		"Gauges": {
			"cats": [
				10
			],
			"js": {
				"_gauges": ""
			},
			"cookies": {
				"_gauges_": ""
			},
			"icon": "Gauges.png",
			"website": "https://get.gaug.es"
		},
		"GitHub Pages": {
			"cats": [
				31
			],
			"url": "^https?://[^/]+\\.github\\.io/",
			"headers": {
				"Server": "^GitHub\\.com$",
				"X-GitHub-Request-Id": ""
			},
			"icon": "GitHub.svg",
			"implies": "Ruby on Rails",
			"website": "https://pages.github.com/"
		},
		"GoStats": {
			"cats": [
				10
			],
			"js": {
				"_goStatsRun": "",
				"_go_track_src": "",
				"go_msie": ""
			},
			"icon": "GoStats.png",
			"website": "http://gostats.com/"
		},
		"Google AdSense": {
			"cats": [
				36
			],
			"js": {
				"google_ad_": "",
				"__google_ad_urls": "",
				"Goog_AdSense_": ""
			},
			"icon": "Google AdSense.svg",
			"script": [
				"googlesyndication\\.com/",
				"ad\\.ca\\.doubleclick\\.net",
				"2mdn\\.net",
				"ad\\.ca\\.doubleclick\\.net"
			],
			"website": "https://www.google.fr/adsense/start/"
		},
		"Google Analytics": {
			"cats": [
				10
			],
			"js": {
				"gaGlobal": "",
				"GoogleAnalyticsObject": ""
			},
			"cookies": {
				"_ga": "",
				"_gat": "",
				"__utma": ""
			},
			"icon": "Google Analytics.svg",
			"script": "google-analytics\\.com\\/(?:ga|urchin|(analytics))\\.js\\;version:\\1?UA:",
			"website": "http://google.com/analytics"
		},
		"Google Analytics Enhanced eCommerce": {
			"cats": [
				10
			],
			"js": {
				"gaplugins.EC": ""
			},
			"icon": "Google Analytics.svg",
			"script": "google-analytics\\.com\\/plugins\\/ua\\/(?:ec|ecommerce)\\.js",
			"implies": "Google Analytics",
			"website": "https://developers.google.com/analytics/devguides/collection/analyticsjs/enhanced-ecommerce"
		},
		"Google Maps": {
			"cats": [
				35
			],
			"icon": "Google Maps.png",
			"script": [
				"(?:maps\\.google\\.com/maps\\?file=api(?:&v=([\\d.]+))?|maps\\.google\\.com/maps/api/staticmap)\\;version:API v\\1",
				"//maps\\.googleapis\\.com/maps/api/js"
			],
			"website": "http://maps.google.com"
		},
		"Google Plus": {
			"cats": [
				5
			],
			"icon": "Google Plus.svg",
			"script": "apis\\.google\\.com/js/[a-z]*\\.js",
			"website": "http://plus.google.com"
		},
		"Google Tag Manager": {
			"cats": [
				42
			],
			"js": {
				"googletag": "",
				"google_tag_manager": ""
			},
			"html": [
				"googletagmanager\\.com/ns\\.html[^>]+></iframe>",
				"<!-- (?:End )?Google Tag Manager -->"
			],
			"icon": "Google Tag Manager.png",
			"website": "http://www.google.com/tagmanager"
		},
		"Google Wallet": {
			"cats": [
				41
			],
			"icon": "Google Wallet.png",
			"script": [
				"checkout\\.google\\.com",
				"wallet\\.google\\.com"
			],
			"website": "http://wallet.google.com"
		},
		"Gravity Insights": {
			"cats": [
				10
			],
			"js": {
				"gravityInsightsParams": ""
			},
			"icon": "Gravity Insights.png",
			"website": "http://insights.gravity.com"
		},
		"HERE": {
			"cats": [
				35
			],
			"icon": "HERE.png",
			"script": "https?://js\\.cit\\.api\\.here\\.com/se/([\\d.]+)\\/\\;version:\\1",
			"website": "http://developer.here.com"
		},
		"Heap": {
			"cats": [
				10
			],
			"js": {
				"heap": ""
			},
			"icon": "Heap.png",
			"script": "heap-\\d+\\.js",
			"website": "http://heapanalytics.com"
		},
		"Hello Bar": {
			"cats": [
				5
			],
			"js": {
				"HelloBar": ""
			},
			"icon": "Hello Bar.png",
			"script": "hellobar\\.js",
			"website": "http://hellobar.com"
		},
		"Hotjar": {
			"cats": [
				10
			],
			"js": {
				"HotLeadfactory": "",
				"HotleadController": "",
				"hj.apiUrlBase": ""
			},
			"icon": "Hotjar.png",
			"script": "^//static\\.hotjar\\.com/c/hotjar-",
			"website": "https://www.hotjar.com"
		},
		"HubSpot": {
			"cats": [
				32
			],
			"js": {
				"_hsq": "",
				"hubspot": ""
			},
			"html": "<!-- Start of Async HubSpot",
			"icon": "HubSpot.png",
			"website": "https://www.hubspot.com"
		},
		"IBM Coremetrics": {
			"cats": [
				10
			],
			"icon": "IBM.svg",
			"script": "cmdatatagutils\\.js",
			"website": "http://ibm.com/software/marketing-solutions/coremetrics"
		},
		"INFOnline": {
			"cats": [
				10
			],
			"js": {
				"szmvars": "",
				"iam_data": ""
			},
			"icon": "INFOnline.png",
			"script": "^https?://(?:[^/]+\\.)?i(?:oam|v)wbox\\.de/",
			"website": "https://www.infonline.de"
		},
		"Incapsula": {
			"cats": [
				31
			],
			"headers": {
				"X-CDN": "Incapsula"
			},
			"icon": "Incapsula.png",
			"website": "http://www.incapsula.com"
		},
		"Infusionsoft": {
			"cats": [
				32
			],
			"html": [
				"<input [^>]*name=\"infusionsoft_version\" [^>]*value=\"([^>]*)\" [^>]*\\/>\\;version:\\1",
				"<input [^>]*value=\"([^>]*)\" [^>]*name=\"infusionsoft_version\" [^>]*\\/>\\;version:\\1"
			],
			"icon": "infusionsoft.svg",
			"website": "http://infusionsoft.com"
		},
		"IntenseDebate": {
			"cats": [
				15
			],
			"icon": "IntenseDebate.png",
			"script": "intensedebate\\.com",
			"website": "http://intensedebate.com"
		},
		"Intercom": {
			"cats": [
				10
			],
			"js": {
				"Intercom": ""
			},
			"icon": "Intercom.png",
			"script": "(?:api\\.intercom\\.io/api|static\\.intercomcdn\\.com/intercom\\.v1)",
			"website": "https://www.intercom.com"
		},
		"INTI": {
			"cats": [
				6,
				53
			],
			"icon": "byINTI.svg",
			"url": "^https?//.+\\.byinti\\.com",
			"website": "http://byinti.com"
		},
		"ip-label": {
			"cats": [
				10
			],
			"script": "clobs\\.js",
			"js": {
				"clobs": ""
			},
			"icon": "iplabel.svg",
			"website": "http://www.ip-label.com"
		},
		"Jirafe": {
			"cats": [
				10,
				32
			],
			"js": {
				"jirafe": ""
			},
			"icon": "Jirafe.png",
			"script": "/jirafe\\.js",
			"website": "https://docs.jirafe.com"
		},
		"KISSmetrics": {
			"cats": [
				10
			],
			"js": {
				"KM_COOKIE_DOMAIN": ""
			},
			"icon": "KISSmetrics.png",
			"website": "https://www.kissmetrics.com"
		},
		"Kampyle": {
			"cats": [
				10,
				13
			],
			"js": {
				"kampyle": "",
				"k_track": "",
				"KAMPYLE_COMMON": ""
			},
			"cookies": {
				"k_visit": ""
			},
			"icon": "Kampyle.png",
			"script": "cf\\.kampyle\\.com/k_button\\.js",
			"website": "http://www.kampyle.com"
		},
		"KeyCDN": {
			"cats": [
				31
			],
			"headers": {
				"Server": "^keycdn-engine$"
			},
			"icon": "KeyCDN.png",
			"website": "http://www.keycdn.com"
		},
		"Klarna Checkout": {
			"cats": [
				41,
				6,
				5
			],
			"js": {
				"_klarnaCheckout": ""
			},
			"icon": "Klarna.svg",
			"website": "https://www.klarna.com/international/"
		},
		"Kontaktify": {
			"cats": [
				5
			],
			"icon": "Kontaktify.png",
			"script": "//(?:www\\.)?kontaktify\\.com/embed\\.js",
			"website": "https://www.kontaktify.com"
		},
		"Laterpay": {
			"cats": [
				41
			],
			"meta": {
				"laterpay:connector:callbacks:on_user_has_access": "deobfuscateText"
			},
			"script": "https?://connectormwi\\.laterpay\\.net/([0-9.]+)[a-zA-z\\-]*/live/[\\w-]+\\.js\\;version:\\1",
			"icon": "laterpay.png",
			"website": "https://www.laterpay.net/"
		},
		"Leaflet": {
			"cats": [
				35
			],
			"js": {
				"L.version": "(.*)\\;version:\\1\\;confidence:0",
				"L.PosAnimation": "",
				"L.DistanceGrid": ""
			},
			"icon": "Leaflet.png",
			"script": "leaflet.*\\.js",
			"website": "http://leafletjs.com"
		},
		"LinkSmart": {
			"cats": [
				36
			],
			"js": {
				"_mb_site_guid": "",
				"LS_JSON": "",
				"LinkSmart": ""
			},
			"icon": "LinkSmart.png",
			"script": "^https?://cdn\\.linksmart\\.com/linksmart_([\\d.]+?)(?:\\.min)?\\.js\\;version:\\1",
			"website": "http://linksmart.com"
		},
		"Linkedin": {
			"cats": [
				5
			],
			"icon": "Linkedin.svg",
			"script": "//platform\\.linkedin\\.com/in\\.js",
			"website": "http://linkedin.com"
		},
		"LiveAgent": {
			"cats": [
				52
			],
			"js": {
				"LiveAgent": ""
			},
			"icon": "LiveAgent.png",
			"website": "https://www.ladesk.com"
		},
		"LiveChat": {
			"cats": [
				52
			],
			"icon": "LiveChat.png",
			"script": "cdn\\.livechatinc\\.com/.*tracking\\.js",
			"website": "http://livechatinc.com"
		},
		"LivePerson": {
			"cats": [
				52
			],
			"icon": "LivePerson.png",
			"script": "^https?://lptag\\.liveperson\\.net/tag/tag\\.js",
			"website": "https://www.liveperson.com/"
		},
		"Livefyre": {
			"cats": [
				15
			],
			"js": {
				"fyre": "",
				"FyreLoader": "",
				"LF.CommentCount": "",
				"L.version": "(.*)\\;confidence:0\\;version:\\1"
			},
			"html": "<[^>]+(?:id|class)=\"livefyre",
			"icon": "Livefyre.png",
			"script": "livefyre_init\\.js",
			"website": "http://livefyre.com"
		},
		"Liveinternet": {
			"cats": [
				10
			],
			"html": [
				"<script[^<>]*>[^]{0,128}?src\\s*=\\s*['\"]//counter\\.yadro\\.ru/hit(?:;\\S+)?\\?(?:t\\d+\\.\\d+;)?r",
				"<!--LiveInternet counter-->",
				"<!--/LiveInternet-->",
				"<a href=\"http://www\\.liveinternet\\.ru/click\""
			],
			"icon": "Liveinternet.png",
			"script": "/js/al/common\\.js\\?[0-9_]+",
			"website": "http://liveinternet.ru/rating/"
		},
		"Luigi’s Box": {
			"cats": [
				10,
				29
			],
			"js": {
				"Luigis": ""
			},
			"icon": "Luigisbox.svg",
			"website": "https://www.luigisbox.com"
		},
		"MadAdsMedia": {
			"cats": [
				36
			],
			"js": {
				"setMIframe": "",
				"setMRefURL": ""
			},
			"icon": "MadAdsMedia.png",
			"script": "^https?://(?:ads-by|pixel)\\.madadsmedia\\.com/",
			"website": "http://madadsmedia.com"
		},
		"MailChimp": {
			"cats": [
				32
			],
			"html": [
				"<form [^>]*data-mailchimp-url",
				"<form [^>]*id=\"mc-embedded-subscribe-form\"",
				"<form [^>]*name=\"mc-embedded-subscribe-form\"",
				"<input [^>]*id=\"mc-email\"\\;confidence:20",
				"<!-- Begin MailChimp Signup Form -->"
			],
			"icon": "mailchimp.svg",
			"script": [
				"s3\\.amazonaws\\.com/downloads\\.mailchimp\\.com/js/mc-validate\\.js",
				"cdn-images\\.mailchimp\\.com/[^>]*\\.css"
			],
			"website": "http://mailchimp.com"
		},
		"ManyContacts": {
			"cats": [
				5
			],
			"icon": "ManyContacts.png",
			"script": "\\/assets\\/js\\/manycontacts\\.min\\.js",
			"website": "http://www.manycontacts.com"
		},
		"Marketo": {
			"cats": [
				32
			],
			"js": {
				"Munchkin": ""
			},
			"icon": "Marketo.png",
			"script": "munchkin\\.marketo\\.net/munchkin\\.js",
			"website": "https://www.marketo.com"
		},
		"MaxCDN": {
			"cats": [
				31
			],
			"headers": {
				"Server": "^NetDNA",
				"X-CDN-Forward": "^maxcdn$"
			},
			"icon": "MaxCDN.png",
			"website": "http://www.maxcdn.com"
		},
		"MediaElement.js": {
			"cats": [
				14
			],
			"js": {
				"mejs": "",
				"mejs.version": "(.*)\\;version:\\1"
			},
			"icon": "MediaElement.js.png",
			"website": "http://www.mediaelementjs.com"
		},
		"Meebo": {
			"cats": [
				5
			],
			"html": "(?:<iframe id=\"meebo-iframe\"|Meebo\\('domReady'\\))",
			"icon": "Meebo.png",
			"website": "http://www.meebo.com"
		},
		"Mint": {
			"cats": [
				10
			],
			"js": {
				"Mint": ""
			},
			"icon": "Mint.png",
			"script": "mint/\\?js",
			"website": "https://haveamint.com"
		},
		"Mixpanel": {
			"cats": [
				10
			],
			"js": {
				"mixpanel": ""
			},
			"icon": "Mixpanel.png",
			"script": "api\\.mixpanel\\.com/track",
			"website": "https://mixpanel.com"
		},
		"Mollom": {
			"cats": [
				16
			],
			"html": "<img[^>]+\\.mollom\\.com",
			"icon": "Mollom.png",
			"script": "mollom(?:\\.min)?\\.js",
			"website": "http://mollom.com"
		},
		"MyBlogLog": {
			"cats": [
				5
			],
			"icon": "MyBlogLog.png",
			"script": "pub\\.mybloglog\\.com",
			"website": "http://www.mybloglog.com"
		},
		"Navegg": {
			"cats": [
				10
			],
			"icon": "Navegg.png",
			"script": "tag\\.navdmp\\.com",
			"website": "https://www.navegg.com/"
		},
		"Netlify": {
			"cats": [
				22,
				31
			],
			"headers": {
				"Server": "Netlify"
			},
			"icon": "Netlify.svg",
			"website": "https://www.netlify.com/"
		},
		"Netmonitor": {
			"cats": [
				10
			],
			"js": {
				"netmonitor": ""
			},
			"icon": "Netmonitor.png",
			"script": "netmonitor\\.fi/nmtracker\\.js",
			"website": "http://netmonitor.fi/en"
		},
		"New Relic": {
			"cats": [
				10
			],
			"js": {
				"NREUM": "",
				"newrelic": ""
			},
			"icon": "New Relic.png",
			"website": "https://newrelic.com"
		},
		"OWL Carousel": {
			"cats": [
				5
			],
			"html": "<link [^>]*href=\"[^\"]+owl\\.carousel(?:\\.min)?\\.css",
			"icon": "OWL Carousel.png",
			"implies": "jQuery",
			"script": "owl\\.carousel.*\\.js",
			"website": "https://owlcarousel2.github.io/OwlCarousel2/"
		},
		"Olark": {
			"cats": [
				52
			],
			"icon": "Olark.png",
			"script": "^https?:\\/\\/static\\.olark\\.com\\/jsclient\\/loader1\\.js",
			"website": "https://www.olark.com/"
		},
		"OneAPM": {
			"cats": [
				10
			],
			"js": {
				"BWEUM": ""
			},
			"icon": "OneAPM.png",
			"website": "http://www.oneapm.com"
		},
		"OneStat": {
			"cats": [
				10
			],
			"js": {
				"OneStat_Pageview": ""
			},
			"icon": "OneStat.png",
			"website": "http://www.onestat.com"
		},
		"Open AdStream": {
			"cats": [
				36
			],
			"js": {
				"OAS_AD": ""
			},
			"icon": "Open AdStream.png",
			"website": "https://www.xaxis.com"
		},
		"Open Web Analytics": {
			"cats": [
				10
			],
			"js": {
				"owa_baseUrl": "",
				"owa_cmds": "",
				"OWA.config.baseUrl": ""
			},
			"html": "<!-- (?:Start|End) Open Web Analytics Tracker -->",
			"icon": "Open Web Analytics.png",
			"website": "http://www.openwebanalytics.com"
		},
		"OpenLayers": {
			"cats": [
				35
			],
			"js": {
				"ol.CanvasMap": "",
				"OpenLayers.VERSION_NUMBER": "([\\d.]+)\\;version:\\1"
			},
			"icon": "OpenLayers.png",
			"script": "openlayers",
			"website": "https://openlayers.org"
		},
		"OpenX": {
			"cats": [
				36
			],
			"icon": "OpenX.png",
			"script": [
				"https?://[^/]*\\.openx\\.net",
				"https?://[^/]*\\.servedbyopenx\\.com"
			],
			"website": "http://openx.com"
		},
		"Optimizely": {
			"cats": [
				10
			],
			"js": {
				"optimizely": ""
			},
			"icon": "Optimizely.png",
			"script": "optimizely\\.com.*\\.js",
			"website": "https://www.optimizely.com"
		},
		"Oracle Recommendations On Demand": {
			"cats": [
				10
			],
			"icon": "Oracle.png",
			"script": "atgsvcs.+atgsvcs\\.js",
			"website": "http://www.oracle.com/us/products/applications/commerce/recommendations-on-demand/index.html"
		},
		"Outbrain": {
			"cats": [
				5
			],
			"js": {
				"OutbrainPermaLink": "",
				"OB_releaseVer": "(.*)\\;version:\\1"
			},
			"icon": "Outbrain.png",
			"script": "widgets\\.outbrain\\.com/outbrain\\.js",
			"website": "https://www.outbrain.com"
		},
		"Pardot": {
			"cats": [
				32
			],
			"js": {
				"piTracker": "",
				"piHostname": "",
				"piProtocol": "",
				"piCId": "",
				"piAId": ""
			},
			"headers": {
				"X-Pardot-LB": "",
				"X-Pardot-Route": "",
				"X-Pardot-Rsp": ""
			},
			"icon": "Pardot.png",
			"website": "https://www.pardot.com"
		},
		"Parse.ly": {
			"cats": [
				10
			],
			"js": {
				"PARSELY": ""
			},
			"icon": "Parse.ly.png",
			"website": "https://www.parse.ly"
		},
		"Braintree": {
			"cats": [
				41
			],
			"js": {
				"Braintree": "",
				"Braintree.version": "(.*)\\;version:\\1"
			},
			"icon": "Braintree.svg",
			"website": "https://www.braintreepayments.com"
		},
		"Adyen": {
			"cats": [
				41
			],
			"js": {
				"adyen.encrypt.version": "(.*)\\;version:\\1"
			},
			"icon": "Adyen.svg",
			"website": "https://www.adyen.com"
		},
		"PayPal": {
			"cats": [
				41
			],
			"js": {
				"PAYPAL": ""
			},
			"html": "<input[^>]+_s-xclick",
			"icon": "PayPal.svg",
			"script": "paypalobjects\\.com/js",
			"website": "https://paypal.com"
		},
		"Pinterest": {
			"cats": [
				5
			],
			"icon": "Pinterest.svg",
			"script": "//assets\\.pinterest\\.com/js/pinit\\.js",
			"website": "http://pinterest.com"
		},
		"Piwik": {
			"cats": [
				10
			],
			"js": {
				"Piwik": "",
				"_paq": ""
			},
			"cookies": {
				"PIWIK_SESSID": ""
			},
			"icon": "Piwik.png",
			"meta": {
				"apple-itunes-app": "app-id=737216887",
				"generator": "Piwik - Open Source Web Analytics",
				"google-play-app": "app-id=org\\.piwik\\.mobile2"
			},
			"script": "piwik\\.js|piwik\\.php",
			"website": "http://piwik.org"
		},
		"Po.st": {
			"cats": [
				5
			],
			"js": {
				"pwidget_config": ""
			},
			"icon": "Po.st.png",
			"website": "http://www.po.st/"
		},
		"Prebid": {
			"cats": [
				36
			],
			"icon": "Prebid.png",
			"js": {
				"pbjs": "",
				"PREBID_TIMEOUT": ""
			},
			"script": [
				"/prebid\\.js",
				"adnxs\\.com/[^\"]*(?:prebid|/pb\\.js)"
			],
			"website": "http://prebid.org"
		},
		"Project Wonderful": {
			"cats": [
				36
			],
			"js": {
				"pw_adloader": ""
			},
			"html": "<div[^>]+id=\"pw_adbox_",
			"icon": "Project Wonderful.png",
			"script": "^https?://(?:www\\.)?projectwonderful\\.com/(?:pwa\\.js|gen\\.php)",
			"website": "http://projectwonderful.com"
		},
		"Prospector": {
			"cats": [
				36
			],
			"html": "<[^>]+data-name=['\"]prospectscript",
			"icon": "Prospector.png",
			"script": "processprospector\\.js",
			"website": "http://prospector.io"
		},
		"Proximis Web to Store": {
			"cats": [
				5,
				6
			],
			"icon": "Proximis Omnichannel.png",
			"script": "widget-commerce(?:\\.min)?\\.js",
			"website": "https://www.proximis.com"
		},
		"PubMatic": {
			"cats": [
				36
			],
			"icon": "PubMatic.png",
			"script": "https?://[^/]*\\.pubmatic\\.com",
			"website": "http://www.pubmatic.com/"
		},
		"Quantcast": {
			"cats": [
				10
			],
			"js": {
				"quantserve": ""
			},
			"icon": "Quantcast.png",
			"script": "\\.quantserve\\.com/quant\\.js",
			"website": "http://www.quantcast.com"
		},
		"Question2Answer": {
			"cats": [
				15
			],
			"html": "<!-- Powered by Question2Answer",
			"icon": "question2answer.png",
			"implies": "PHP",
			"script": "\\./qa-content/qa-page\\.js\\?([0-9.]+)\\;version:\\1",
			"website": "http://www.question2answer.org"
		},
		"RD Station": {
			"cats": [
				32
			],
			"js": {
				"RDStation": ""
			},
			"icon": "RD Station.png",
			"script": "d335luupugsy2\\.cloudfront\\.net/js/loader-scripts/.*-loader\\.js",
			"website": "http://rdstation.com.br"
		},
		"Reinvigorate": {
			"cats": [
				10
			],
			"js": {
				"reinvigorate": ""
			},
			"icon": "Reinvigorate.png",
			"website": "http://www.reinvigorate.net"
		},
		"RockRMS": {
			"cats": [
				1,
				11,
				32
			],
			"icon": "RockRMS.svg",
			"implies": [
				"Windows Server",
				"IIS",
				"Microsoft ASP.NET"
			],
			"meta": {
				"generator": "^Rock v.*"
			},
			"website": "http://www.rockrms.com"
		},
		"Rubicon Project": {
			"cats": [
				36
			],
			"icon": "Rubicon Project.png",
			"script": "https?://[^/]*\\.rubiconproject\\.com",
			"website": "http://rubiconproject.com/"
		},
		"Ruxit": {
			"cats": [
				10
			],
			"icon": "Ruxit.png",
			"script": "ruxitagentjs",
			"website": "http://ruxit.com"
		},
		"Salesforce": {
			"cats": [
				53
			],
			"js": {
				"SFDCApp": "",
				"SFDCCmp": "",
				"SFDCPage": "",
				"SFDCSessionVars": ""
			},
			"cookies": {
				"com.salesforce": ""
			},
			"html": "<[^>]+=\"brandQuaternaryFgrs\"",
			"icon": "Salesforce.svg",
			"website": "https://www.salesforce.com"
		},
		"Segment": {
			"cats": [
				10
			],
			"js": {
				"analytics": ""
			},
			"html": "<script[\\s\\S]*cdn\\.segment\\.com/analytics\\.js[\\s\\S]*script>",
			"icon": "Segment.png",
			"script": "cdn\\.segment\\.com/analytics\\.js",
			"website": "http://segment.com"
		},
		"ShareThis": {
			"cats": [
				5
			],
			"js": {
				"SHARETHIS": ""
			},
			"icon": "ShareThis.png",
			"script": "w\\.sharethis\\.com/",
			"website": "http://sharethis.com"
		},
		"ShinyStat": {
			"cats": [
				10
			],
			"js": {
				"SSsdk": ""
			},
			"html": "<img[^>]*\\s+src=['\"]?https?://www\\.shinystat\\.com/cgi-bin/shinystat\\.cgi\\?[^'\"\\s>]*['\"\\s/>]",
			"icon": "ShinyStat.png",
			"script": "^https?://codice(?:business|ssl|pro|isp)?\\.shinystat\\.com/cgi-bin/getcod\\.cgi",
			"website": "http://shinystat.com"
		},
		"Shopalize": {
			"cats": [
				5,
				10
			],
			"js": {
				"Shopalize": ""
			},
			"icon": "Shopalize.png",
			"website": "http://shopalize.com"
		},
		"Site Meter": {
			"cats": [
				10
			],
			"icon": "Site Meter.png",
			"script": "sitemeter\\.com/js/counter\\.js\\?site=",
			"website": "http://www.sitemeter.com"
		},
		"SiteCatalyst": {
			"cats": [
				10
			],
			"js": {
				"s_account": "",
				"s_objectID": "",
				"s_code": "",
				"s_INST": ""
			},
			"icon": "SiteCatalyst.png",
			"script": "/s[_-]code.*\\.js",
			"website": "http://www.adobe.com/solutions/digital-marketing.html"
		},
		"Sizmek": {
			"cats": [
				36
			],
			"html": "(?:<a [^>]*href=\"[^/]*//[^/]*serving-sys\\.com/|<img [^>]*src=\"[^/]*//[^/]*serving-sys\\.com/)",
			"icon": "Sizmek.png",
			"script": "serving-sys\\.com/",
			"website": "http://sizmek.com"
		},
		"Smart Ad Server": {
			"cats": [
				36
			],
			"js": {
				"SmartAdServer": ""
			},
			"html": "<img[^>]+smartadserver\\.com\\/call",
			"icon": "Smart Ad Server.png",
			"website": "http://smartadserver.com"
		},
		"Snoobi": {
			"cats": [
				10
			],
			"js": {
				"snoobi": ""
			},
			"icon": "Snoobi.png",
			"script": "snoobi\\.com/snoop\\.php",
			"website": "http://www.snoobi.com"
		},
		"Solve Media": {
			"cats": [
				16,
				36
			],
			"js": {
				"_ACPuzzle": "",
				"ACPuzzle": "",
				"_adcopy-puzzle-image-image": "",
				"adcopy-puzzle-image-image": ""
			},
			"icon": "Solve Media.png",
			"script": "^https?://api\\.solvemedia\\.com/",
			"website": "http://solvemedia.com"
		},
		"Stackla": {
			"cats": [
				5
			],
			"js": {
				"Stackla": ""
			},
			"icon": "Stackla.png",
			"script": "assetscdn\\.stackla\\.com\\/media\\/js\\/widget\\/(?:[a-zA-Z0-9.]+)?\\.js",
			"website": "http://stackla.com/"
		},
		"Statcounter": {
			"cats": [
				10
			],
			"icon": "Statcounter.svg",
			"js": {
				"_statcounter": "\\;confidence:100",
				"sc_project": "\\;confidence:50",
				"sc_security": "\\;confidence:50"
			},
			"script": "statcounter\\.com/counter/counter",
			"website": "http://www.statcounter.com"
		},
		"Stripe": {
			"cats": [
				41
			],
			"js": {
				"Stripe.version": "(.*)\\;version:\\1"
			},
			"html": "<input[^>]+data-stripe",
			"icon": "Stripe.png",
			"script": "js\\.stripe\\.com",
			"website": "http://stripe.com"
		},
		"SublimeVideo": {
			"cats": [
				14
			],
			"js": {
				"sublimevideo": ""
			},
			"icon": "SublimeVideo.png",
			"script": "cdn\\.sublimevideo\\.net/js/[a-z\\d]+\\.js",
			"website": "http://sublimevideo.net"
		},
		"SumoMe": {
			"cats": [
				5,
				32
			],
			"icon": "SumoMe.png",
			"script": "load\\.sumome\\.com",
			"website": "http://sumome.com"
		},
		"Tawk.to": {
			"cats": [
				52
			],
			"icon": "TawkTo.png",
			"script": "//embed\\.tawk\\.to",
			"website": "http://tawk.to"
		},
		"Tealeaf": {
			"cats": [
				10
			],
			"js": {
				"TeaLeaf": ""
			},
			"icon": "Tealeaf.png",
			"website": "http://www.tealeaf.com"
		},
		"Tealium": {
			"cats": [
				36
			],
			"js": {
				"TEALIUMENABLED": ""
			},
			"icon": "Tealium.png",
			"script": [
				"^//tags\\.tiqcdn\\.com/",
				"/tealium/utag\\.js$"
			],
			"website": "http://tealium.com"
		},
		"Titan": {
			"cats": [
				36
			],
			"js": {
				"titan": "",
				"titanEnabled": ""
			},
			"html": "<script[^>]+>var titan",
			"icon": "Titan.png",
			"website": "http://titan360.com"
		},
		"TrackJs": {
			"cats": [
				10
			],
			"js": {
				"TrackJs": ""
			},
			"icon": "TrackJs.png",
			"script": "tracker\\.js",
			"website": "http://trackjs.com"
		},
		"Twitter": {
			"cats": [
				5
			],
			"icon": "Twitter.svg",
			"script": "//platform\\.twitter\\.com/widgets\\.js",
			"website": "http://twitter.com"
		},
		"UserEngage": {
			"cats": [
				10
			],
			"js": {
				"UserEngage": ""
			},
			"icon": "UserEngage.png",
			"html": "<div[^>]+/id=\"ue_widget\"",
			"website": "https://userengage.com"
		},
		"UserLike": {
			"cats": [
				52
			],
			"icon": "UserLike.svg",
			"script": [
				"userlike\\.min\\.js",
				"userlikelib\\.min\\.js"
			],
			"website": "http://userlike.com"
		},
		"Ushahidi": {
			"cats": [
				1,
				35
			],
			"js": {
				"Ushahidi": ""
			},
			"cookies": {
				"ushahidi": ""
			},
			"icon": "Ushahidi.png",
			"implies": [
				"PHP",
				"MySQL",
				"OpenLayers"
			],
			"script": "/js/ushahidi\\.js$",
			"website": "http://www.ushahidi.com"
		},
		"Veoxa": {
			"cats": [
				36
			],
			"js": {
				"VuVeoxaContent": ""
			},
			"html": "<img [^>]*src=\"[^\"]+tracking\\.veoxa\\.com",
			"icon": "Veoxa.png",
			"script": "tracking\\.veoxa\\.com",
			"website": "http://veoxa.com"
		},
		"VideoJS": {
			"cats": [
				14
			],
			"js": {
				"VideoJS": ""
			},
			"html": "<div[^>]+class=\"video-js+\">",
			"icon": "VideoJS.png",
			"script": "zencdn\\.net/c/video\\.js",
			"website": "http://videojs.com"
		},
		"VigLink": {
			"cats": [
				36
			],
			"js": {
				"vglnk": "",
				"vl_cB": "",
				"vl_disable": ""
			},
			"icon": "VigLink.png",
			"script": "(?:^[^/]*//[^/]*viglink\\.com/api/|vglnk\\.js)",
			"website": "http://viglink.com"
		},
		"Vimeo": {
			"cats": [
				14
			],
			"html": "(?:<(?:param|embed)[^>]+vimeo\\.com/moogaloop|<iframe[^>]player\\.vimeo\\.com)",
			"icon": "Vimeo.png",
			"website": "http://vimeo.com"
		},
		"VisualPath": {
			"cats": [
				10
			],
			"icon": "VisualPath.png",
			"script": "visualpath[^/]*\\.trackset\\.it/[^/]+/track/include\\.js",
			"website": "http://www.trackset.com/web-analytics-software/visualpath"
		},
		"W3Counter": {
			"cats": [
				10
			],
			"icon": "W3Counter.png",
			"script": "w3counter\\.com/tracker\\.js",
			"website": "http://www.w3counter.com"
		},
		"Web Optimizer": {
			"cats": [
				10
			],
			"html": "<title [^>]*lang=\"wo\">",
			"icon": "Web Optimizer.png",
			"website": "http://www.web-optimizer.us"
		},
		"Webtrekk": {
			"cats": [
				10
			],
			"js": {
				"webtrekk": ""
			},
			"icon": "Webtrekk.png",
			"website": "http://www.webtrekk.com"
		},
		"Webtrends": {
			"cats": [
				10
			],
			"js": {
				"WTOptimize": "",
				"WebTrends": ""
			},
			"html": "<img[^>]+id=\"DCSIMG\"[^>]+webtrends",
			"icon": "Webtrends.png",
			"website": "http://worldwide.webtrends.com"
		},
		"Woopra": {
			"cats": [
				10
			],
			"icon": "Woopra.png",
			"script": "static\\.woopra\\.com",
			"website": "http://www.woopra.com"
		},
		"Yahoo Advertising": {
			"cats": [
				36
			],
			"js": {
				"adxinserthtml": ""
			},
			"html": [
				"<iframe[^>]+adserver\\.yahoo\\.com",
				"<img[^>]+clicks\\.beap\\.bc\\.yahoo\\.com"
			],
			"icon": "yahoo.png",
			"script": "adinterax\\.com",
			"website": "http://advertising.yahoo.com"
		},
		"Yahoo! Web Analytics": {
			"cats": [
				10
			],
			"js": {
				"YWA": ""
			},
			"icon": "yahoo.png",
			"script": "d\\.yimg\\.com/mi/ywa\\.js",
			"website": "http://web.analytics.yahoo.com"
		},
		"Yandex.Direct": {
			"cats": [
				36
			],
			"js": {
				"yandex_partner_id": "",
				"yandex_ad_format": ""
			},
			"html": "<yatag class=\"ya-partner__ads\">",
			"icon": "Yandex.Direct.png",
			"script": "https?://an\\.yandex\\.ru/",
			"website": "http://partner.yandex.com"
		},
		"Yandex.Metrika": {
			"cats": [
				10
			],
			"js": {
				"yandex_metrika": ""
			},
			"icon": "Yandex.Metrika.png",
			"script": [
				"mc\\.yandex\\.ru\\/metrika\\/watch\\.js",
				"cdn\\.jsdelivr\\.net\\/npm\\/yandex-metrica-watch\\/watch\\.js"
			],
			"website": "http://metrika.yandex.com"
		},
		"Yieldlab": {
			"cats": [
				36
			],
			"icon": "Yieldlab.png",
			"script": "^https?://(?:[^/]+\\.)?yieldlab\\.net/",
			"website": "http://yieldlab.de"
		},
		"YouTube": {
			"cats": [
				14
			],
			"html": "<(?:param|embed|iframe)[^>]+youtube(?:-nocookie)?\\.com/(?:v|embed)",
			"icon": "YouTube.png",
			"website": "http://www.youtube.com"
		},
		"Zanox": {
			"cats": [
				36
			],
			"js": {
				"zanox": ""
			},
			"html": "<img [^>]*src=\"[^\"]+ad\\.zanox\\.com",
			"icon": "Zanox.png",
			"script": "zanox\\.com/scripts/zanox\\.js$",
			"website": "http://zanox.com"
		},
		"Zendesk Chat": {
			"cats": [
				52
			],
			"icon": "Zendesk Chat.png",
			"script": "v2\\.zopim\\.com",
			"website": "http://zopim.com"
		},
		"comScore": {
			"cats": [
				10
			],
			"js": {
				"COMSCORE": "",
				"_COMSCORE": ""
			},
			"html": "<iframe[^>]* (?:id=\"comscore\"|scr=[^>]+comscore)|\\.scorecardresearch\\.com/beacon\\.js|COMSCORE\\.beacon",
			"icon": "comScore.png",
			"script": "\\.scorecardresearch\\.com/beacon\\.js|COMSCORE\\.beacon",
			"website": "http://comscore.com"
		},
		"LiveHelp": {
			"cats": [
				52,
				53
			],
			"script": "^https?://server\\.livehelp\\.it/widgetjs/[0-9]{5}/[0-9]{1,3}\\.js",
			"icon": "LiveHelp.png",
			"website": "http://www.livehelp.it"
		},
		"reCAPTCHA": {
			"cats": [
				16
			],
			"js": {
				"Recaptcha": ""
			},
			"html": "(?:<div[^>]+id=\"recaptcha_image|<link[^>]+recaptcha|document\\.getElementById\\('recaptcha')",
			"icon": "reCAPTCHA.png",
			"script": "(?:api-secure\\.recaptcha\\.net|recaptcha_ajax\\.js)",
			"website": "https://www.google.com/recaptcha/"
		},
		"Raychat": {
			"cats": [
				52
			],
			"js": {
				"Raychat": ""
			},
			"icon": "raychat.png",
			"script": "app\\.raychat\\.io/scripts/js",
			"website": "https://raychat.io"
		},
		"Mautic": {
			"cats": [
				32
			],
			"js": {
				"MauticTrackingObject": ""
			},
			"icon": "mautic.svg",
			"script": "[^a-z]mtc.*\\.js",
			"website": "https://www.mautic.org/"
		},
		"Anetwork": {
			"cats": [
				36
			],
			"icon": "Anetwork.png",
			"script": "static-cdn\\.anetwork\\.ir/",
			"website": "https://www.anetwork.ir"
		},
		"Freshmarketer": {
			"cats": [
				10
			],
			"script": "cdn\\.freshmarketer\\.com",
			"icon": "freshmarketer.png",
			"website": "https://www.freshworks.com/marketing-automation/conversion-rate-optimization/"
		},
		"GoSquared": {
			"cats": [
				10,
				52,
				53
			],
			"js": {
				"_gs": "\\;confidence:30"
			},
			"icon": "gosquared.png",
			"website": "https://www.gosquared.com/"
		},
		"Amplitude": {
			"cats": [
				10
			],
			"script": [
				"cdn\\.amplitude\\.com"
			],
			"icon": "amplitude.png",
			"website": "https://amplitude.com/"
		},
		"Inspectlet": {
			"cats": [
				10
			],
			"html": [
				"<!-- (?:Begin|End) Inspectlet Embed Code -->"
			],
			"script": [
				"cdn\\.inspectlet\\.com"
			],
			"js": {
				"__insp": "",
				"__inspld": ""
			},
			"icon": "inspectlet.png",
			"website": "https://www.inspectlet.com/"
		},
		"Mouse Flow": {
			"cats": [
				10
			],
			"js": {
				"_mfq": ""
			},
			"script": [
				"cdn\\.mouseflow\\.com"
			],
			"icon": "mouseflow.png",
			"website": "https://mouseflow.com/"
		},
		"Visual Website Optimizer": {
			"cats": [
				10
			],
			"html": [
				"<!-- (?:Start|End) Visual Website Optimizer A?Synchronous Code -->"
			],
			"script": [
				"dev\\.visualwebsiteoptimizer\\.com"
			],
			"js": {
				"VWO": "",
				"__vwo": ""
			},
			"icon": "vwo.svg",
			"website": "https://vwo.com/"
		}
	},
	"categories": {
		"1": {
			"name": "CMS",
			"priority": 1
		},
		"2": {
			"name": "Message Boards",
			"priority": 1
		},
		"3": {
			"name": "Database Managers",
			"priority": 2
		},
		"4": {
			"name": "Documentation Tools",
			"priority": 2
		},
		"5": {
			"name": "Widgets",
			"priority": 9
		},
		"6": {
			"name": "Ecommerce",
			"priority": 1
		},
		"7": {
			"name": "Photo Galleries",
			"priority": 1
		},
		"8": {
			"name": "Wikis",
			"priority": 1
		},
		"9": {
			"name": "Hosting Panels",
			"priority": 1
		},
		"10": {
			"name": "Analytics",
			"priority": 9
		},
		"11": {
			"name": "Blogs",
			"priority": 1
		},
		"12": {
			"name": "JavaScript Frameworks",
			"priority": 5
		},
		"13": {
			"name": "Issue Trackers",
			"priority": 2
		},
		"14": {
			"name": "Video Players",
			"priority": 7
		},
		"15": {
			"name": "Comment Systems",
			"priority": 9
		},
		"16": {
			"name": "Captchas",
			"priority": 9
		},
		"17": {
			"name": "Font Scripts",
			"priority": 9
		},
		"18": {
			"name": "Web Frameworks",
			"priority": 4
		},
		"19": {
			"name": "Miscellaneous",
			"priority": 9
		},
		"20": {
			"name": "Editors",
			"priority": 4
		},
		"21": {
			"name": "LMS",
			"priority": 1
		},
		"22": {
			"name": "Web Servers",
			"priority": 7
		},
		"23": {
			"name": "Cache Tools",
			"priority": 9
		},
		"24": {
			"name": "Rich Text Editors",
			"priority": 5
		},
		"25": {
			"name": "JavaScript Graphics",
			"priority": 3
		},
		"26": {
			"name": "Mobile Frameworks",
			"priority": 3
		},
		"27": {
			"name": "Programming Languages",
			"priority": 4
		},
		"28": {
			"name": "Operating Systems",
			"priority": 5
		},
		"29": {
			"name": "Search Engines",
			"priority": 4
		},
		"30": {
			"name": "Web Mail",
			"priority": 2
		},
		"31": {
			"name": "CDN",
			"priority": 9
		},
		"32": {
			"name": "Marketing Automation",
			"priority": 9
		},
		"33": {
			"name": "Web Server Extensions",
			"priority": 7
		},
		"34": {
			"name": "Databases",
			"priority": 5
		},
		"35": {
			"name": "Maps",
			"priority": 9
		},
		"36": {
			"name": "Advertising Networks",
			"priority": 9
		},
		"37": {
			"name": "Network Devices",
			"priority": 9
		},
		"38": {
			"name": "Media Servers",
			"priority": 1
		},
		"39": {
			"name": "Webcams",
			"priority": 9
		},
		"40": {
			"name": "Printers",
			"priority": 9
		},
		"41": {
			"name": "Payment Processors",
			"priority": 8
		},
		"42": {
			"name": "Tag Managers",
			"priority": 9
		},
		"43": {
			"name": "Paywalls",
			"priority": 9
		},
		"44": {
			"name": "Build CI Systems",
			"priority": 4
		},
		"45": {
			"name": "Control Systems",
			"priority": 8
		},
		"46": {
			"name": "Remote Access",
			"priority": 8
		},
		"47": {
			"name": "Dev Tools",
			"priority": 3
		},
		"48": {
			"name": "Network Storage",
			"priority": 9
		},
		"49": {
			"name": "Feed Readers",
			"priority": 1
		},
		"50": {
			"name": "Document Management Systems",
			"priority": 1
		},
		"51": {
			"name": "Landing Page Builders",
			"priority": 2
		},
		"52": {
			"name": "Live Chat",
			"priority": 9
		},
		"53": {
			"name": "CRM",
			"priority": 7
		},
		"54": {
			"name": "SEO",
			"priority": 7
		},
		"55": {
			"name": "Accounting",
			"priority": 1
		},
		"56": {
			"name": "Cryptominer",
			"priority": 8
		},
		"57": {
			"name": "Static Site Generator",
			"priority": 1
		}
	}
}